django_toolkit/__init__.py
django_toolkit/middlewares.py
django_toolkit/shortcuts.py
django_toolkit/toolkit_settings.py
django_toolkit/concurrent/__init__.py
django_toolkit/concurrent/locks.py
django_toolkit/fallbacks/__init__.py
django_toolkit/fallbacks/circuit_breaker/__init__.py
django_toolkit/fallbacks/circuit_breaker/circuit_breaker.py
django_toolkit/fallbacks/circuit_breaker/rules.py
django_toolkit/logs/__init__.py
django_toolkit/logs/filters.py
django_toolkit/oauth2/__init__.py
django_toolkit/oauth2/apps.py
django_toolkit/oauth2/receivers.py
django_toolkit/oauth2/validators.py
luizalabs_django_toolkit-2.2.0.dist-info/LICENSE
luizalabs_django_toolkit-2.2.0.dist-info/METADATA
luizalabs_django_toolkit-2.2.0.dist-info/WHEEL
luizalabs_django_toolkit-2.2.0.dist-info/top_level.txt
luizalabs_django_toolkit-2.2.0.dist-info/RECORD
