Metadata-Version: 2.1
Name: luizalabs-django-toolkit
Version: 2.2.0
Summary: The LuizaLabs set of tools to develop projects using the Django framework
Home-page: https://github.com/luizalabs/django-toolkit
Author: Luizalabs
Author-email: pypi@luizalabs.com
License: UNKNOWN
Keywords: django tools logs middleware utils
Platform: UNKNOWN
Classifier: Framework :: Django
Classifier: Intended Audience :: Developers
Classifier: License :: OSI Approved :: MIT License
Classifier: Operating System :: OS Independent
Classifier: Programming Language :: Python :: 2
Classifier: Programming Language :: Python :: 3
Requires-Dist: Django (>=1.8)
Provides-Extra: oauth2
Requires-Dist: django-oauth-toolkit (==1.0.0) ; extra == 'oauth2'
